pcte_dynaprov/__init__.py
pcte_dynaprov/parsers.py
pcte_dynaprov/services/__init__.py
pcte_dynaprov/services/monitor_api.py
pcte_dynaprov/services/rmq_listener.py
pcte_dynaprov/validators.py
pcte_dynamic_provisioning-0.1.0.dist-info/entry_points.txt
pcte_dynamic_provisioning-0.1.0.dist-info/WHEEL
pcte_dynamic_provisioning-0.1.0.dist-info/METADATA
pcte_dynamic_provisioning-0.1.0.dist-info/RECORD
