Metadata-Version: 2.1
Name: pcte-dynamic-provisioning
Version: 0.1.0
Summary: Dynamic Provisioning of the PCTE Greyspace Environment
Home-page: UNKNOWN
License: UNKNOWN
Author: Jordan Gregory
Author-email: jordan.gregory@metova.com
Requires-Python: >=3.6,<4.0
Classifier: Programming Language :: Python :: 3
Classifier: Programming Language :: Python :: 3.6
Classifier: Programming Language :: Python :: 3.7
Requires-Dist: PyYAML (>=3.13,<4.0)
Requires-Dist: aiohttp (>=3.4,<4.0)
Requires-Dist: click (>=7.0,<8.0)
Requires-Dist: jsonschema (>=2.6,<3.0)
Requires-Dist: pika (>=0.12.0,<0.13.0)
Requires-Dist: pyvmomi (>=6.7,<7.0)
Project-URL: Documentation, https://cybercents.atlassian.com/pcte
